forgeit/cli.py
forgeit/db.py
forgeit/engine.py
forgeit/env.py
forgeit/input.py
forgeit/meta.py
forgeit/model.py
forgeit/processors.py
forgeit/schemas.py
forgeit/template.py
forgeit/utils.py
forgeit/data/flask-api.zip
forgeit-0.1.0b2.dist-info/licenses/LICENSE
forgeit-0.1.0b2.dist-info/METADATA
forgeit-0.1.0b2.dist-info/WHEEL
forgeit-0.1.0b2.dist-info/entry_points.txt
forgeit-0.1.0b2.dist-info/top_level.txt
forgeit-0.1.0b2.dist-info/RECORD
