Metadata-Version: 2.4
Name: forgeit
Version: 0.1.0b2
Summary: A simple cli tool to generate python project based on a template
Author-email: Kenneth Ulloa <ulloakenth@gmail.com>
License-Expression: MIT
Project-URL: Homepage, https://github.com/KennethUlloa/forgeit
Keywords: cli,python,template,project,scaffold,tool
Classifier: Intended Audience :: Developers
Classifier: Operating System :: OS Independent
Classifier: Programming Language :: Python :: 3
Classifier: Programming Language :: Python :: 3.10
Classifier: Topic :: Software Development :: Code Generators
Classifier: Topic :: Software Development :: Libraries :: Python Modules
Classifier: Topic :: Utilities
Requires-Python: >=3.10
License-File: LICENSE
Requires-Dist: Jinja2>=3.1.4
Requires-Dist: typer>=0.15.2
Requires-Dist: jsonschema>=4.23.0
Dynamic: license-file
